stockaggregator/__init__.py
stockaggregator/aggregate.py
StockAggregator-0.3.dist-info/METADATA
StockAggregator-0.3.dist-info/WHEEL
StockAggregator-0.3.dist-info/dependency_links.txt
StockAggregator-0.3.dist-info/top_level.txt
StockAggregator-0.3.dist-info/RECORD
