Metadata-Version: 2.1
Name: StockAggregator
Version: 0.3
Summary: UNKNOWN
Home-page: http://github.com/
Author: Yasin Denktas-Yildiz
Author-email: yasin.denktas@essec.edu
License: MIT
Platform: UNKNOWN
Requires-Python: >=3.7.1
Requires-Dist: requests
